auxiliary_scripts/__init__.py
auxiliary_scripts/add_tc_score.py
auxiliary_scripts/alter_pfamsjs.py
auxiliary_scripts/check_domstats_overlap.py
auxiliary_scripts/convert2json.py
auxiliary_scripts/extr_domhits_from_domtab.py
auxiliary_scripts/fetch_ncbi_genomes_mgb.py
auxiliary_scripts/get_antismash_classes.py
auxiliary_scripts/get_classes.py
auxiliary_scripts/link_mods_bgcs.py
auxiliary_scripts/link_subcluster_ids.py
auxiliary_scripts/make_arrower_from_jsons.py
auxiliary_scripts/parse_dom.py
auxiliary_scripts/parse_json2clusterfile.py
auxiliary_scripts/plot_convergence.py
auxiliary_scripts/replace_domains.py
auxiliary_scripts/run_multiple_lda.py
correlation_analysis/__init__.py
correlation_analysis/correlate_molecular_motifs_to_subclusters.py
correlation_analysis/extract_crusemann_topic_matches.py
iPRESTO-1.0.3.data/scripts/add_tc_score.py
iPRESTO-1.0.3.data/scripts/alter_pfamsjs.py
iPRESTO-1.0.3.data/scripts/bgc_to_pfam.py
iPRESTO-1.0.3.data/scripts/check_domstats_overlap.py
iPRESTO-1.0.3.data/scripts/cluster_families.py
iPRESTO-1.0.3.data/scripts/cluster_stat_modules.py
iPRESTO-1.0.3.data/scripts/convert2json.py
iPRESTO-1.0.3.data/scripts/correlate_molecular_motifs_to_subclusters.py
iPRESTO-1.0.3.data/scripts/extr_domhits_from_domtab.py
iPRESTO-1.0.3.data/scripts/extract_crusemann_topic_matches.py
iPRESTO-1.0.3.data/scripts/fetch_ncbi_genomes_mgb.py
iPRESTO-1.0.3.data/scripts/filter_bgcs.py
iPRESTO-1.0.3.data/scripts/filter_statistical_method.py
iPRESTO-1.0.3.data/scripts/get_antismash_classes.py
iPRESTO-1.0.3.data/scripts/get_classes.py
iPRESTO-1.0.3.data/scripts/link_mods_bgcs.py
iPRESTO-1.0.3.data/scripts/link_statistical_modules2subclusterblast.py
iPRESTO-1.0.3.data/scripts/link_subcluster_ids.py
iPRESTO-1.0.3.data/scripts/list_stat_modules.py
iPRESTO-1.0.3.data/scripts/make_arrower_from_jsons.py
iPRESTO-1.0.3.data/scripts/parent_modules.py
iPRESTO-1.0.3.data/scripts/parent_modules_clans.py
iPRESTO-1.0.3.data/scripts/parse_dom.py
iPRESTO-1.0.3.dist-info/LICENSE
iPRESTO-1.0.3.dist-info/METADATA
iPRESTO-1.0.3.dist-info/WHEEL
iPRESTO-1.0.3.dist-info/top_level.txt
iPRESTO-1.0.3.dist-info/RECORD
