Metadata-Version: 2.1
Name: iPRESTO
Version: 1.0.3
Summary: Detection of biosynthetic sub-clusters
Home-page: https://git.wageningenur.nl/bioinformatics/iPRESTO
Author: Joris Louwen
Author-email: jorislouwen@hotmail.com
License: UNKNOWN
Platform: UNKNOWN
Classifier: Programming Language :: Python :: 3
Classifier: License :: OSI Approved :: GNU Affero General Public License v3
Classifier: Operating System :: OS Independent
Requires-Python: >=3.6
Requires-Dist: biopython
Requires-Dist: matplotlib
Requires-Dist: networkx
Requires-Dist: numpy
Requires-Dist: gensim
Requires-Dist: pyLDAvis
Requires-Dist: pandas
Requires-Dist: scipy
Requires-Dist: seaborn
Requires-Dist: statsmodels
Requires-Dist: sympy
